finnslib/__init__.py
finnslib/cli.py
finnslib/version.py
finnslib/repo/__init__.py
finnslib/repo/tree.py
finnslib/summarise/__init__.py
finnslib/summarise/cache.py
finnslib/summarise/file.py
finnslib/summarise/function.py
finnslib/summarise/tree_with_files.py
finnslib-0.1.3.dist-info/licenses/LICENSE
finnslib-0.1.3.dist-info/METADATA
finnslib-0.1.3.dist-info/WHEEL
finnslib-0.1.3.dist-info/entry_points.txt
finnslib-0.1.3.dist-info/top_level.txt
finnslib-0.1.3.dist-info/RECORD
