Metadata-Version: 2.4
Name: finnslib
Version: 0.1.3
Summary: helper functions for working with codebases. summarize files, functions, and repository trees using the openai api
Author-email: Finn Clancy <finnnclancy2000@gmail.com>
License: MIT
Project-URL: Homepage, https://github.com/finnclancy/finnslib
Project-URL: Repository, https://github.com/finnclancy/finnslib
Project-URL: Issues, https://github.com/finnclancy/finnslib/issues
Keywords: tree,gitignore,summary,llm,code,openai,documentation
Classifier: Development Status :: 4 - Beta
Classifier: Intended Audience :: Developers
Classifier: Operating System :: OS Independent
Classifier: Programming Language :: Python :: 3
Classifier: Programming Language :: Python :: 3.9
Classifier: Programming Language :: Python :: 3.10
Classifier: Programming Language :: Python :: 3.11
Classifier: Programming Language :: Python :: 3.12
Classifier: Programming Language :: Python :: 3.13
Classifier: Topic :: Software Development :: Documentation
Classifier: Topic :: Software Development :: Libraries :: Python Modules
Classifier: Topic :: Text Processing :: Linguistic
Requires-Python: >=3.9
License-File: LICENSE
Requires-Dist: openai>=1.0
Provides-Extra: dev
Requires-Dist: pytest>=7.0; extra == "dev"
Requires-Dist: pytest-cov>=4.0; extra == "dev"
Requires-Dist: black>=22.0; extra == "dev"
Requires-Dist: flake8>=5.0; extra == "dev"
Requires-Dist: mypy>=1.0; extra == "dev"
Dynamic: license-file
